patterns/__init__.py
patterns/doji.py
patterns/dragonfly_doji.py
patterns/engulfing.py
patterns/gravestone_doji.py
patterns/hammer.py
patterns/hanging_man.py
patterns/harami.py
patterns/inverted_hammer.py
patterns/longlegged_doji.py
patterns/pattern.py
patterns/shooting_star.py
patterns/three_black_crows.py
patterns/three_white_soldiers.py
patterns/test/__init__.py
patterns/test/conftest.py
patterns/test/test_doji.py
patterns/test/test_dragonfly_doji.py
patterns/test/test_engulfing.py
patterns/test/test_gravestone_doji.py
patterns/test/test_hammer.py
patterns/test/test_hanging_man.py
patterns/test/test_harami.py
patterns/test/test_inverted_hammer.py
patterns/test/test_longlegged_doji.py
patterns/test/test_pattern.py
patterns/test/test_shooting_star.py
patterns/test/test_three_black_crows.py
patterns/test/test_three_white_soldiers.py
japanese_candlestick-0.2.0.dist-info/LICENSE
japanese_candlestick-0.2.0.dist-info/METADATA
japanese_candlestick-0.2.0.dist-info/WHEEL
japanese_candlestick-0.2.0.dist-info/top_level.txt
japanese_candlestick-0.2.0.dist-info/RECORD
