Metadata-Version: 2.1
Name: japanese-candlestick
Version: 0.2.0
Summary: Japanese candlestick pattern
Home-page: https://github.com/vincent-vdb/japanese-candlestick-pattern
Author: Vincent Vandenbussche
Author-email: vandenbussche.vincent@gmail.com
License: MIT
Project-URL: Bug Tracker, https://github.com/pypa/sampleproject/issues
Keywords: trading candlestick analysis
Classifier: Programming Language :: Python :: 3
Classifier: License :: OSI Approved :: MIT License
Classifier: Operating System :: OS Independent
Classifier: Topic :: Scientific/Engineering :: Mathematics
License-File: LICENSE
Requires-Dist: numpy (==1.22.3)
Requires-Dist: pandas (==1.4.2)
Requires-Dist: python-binance (==1.0.16)
Requires-Dist: telegram-send (==0.33.1)
Requires-Dist: schedule (==1.1.0)
